{"id":"getMood.js","dependencies":[{"name":"/Users/mattiasrademar/Documents/Webbutveckling/mood/package.json","includedInParent":true,"mtime":1536747649597},{"name":"./lineChart","loc":{"line":1,"column":20},"parent":"/Users/mattiasrademar/Documents/Webbutveckling/mood/getMood.js","resolved":"/Users/mattiasrademar/Documents/Webbutveckling/mood/lineChart.js"}],"generated":{"js":"'use strict';\n\nvar _lineChart = require('./lineChart');\n\nvar _lineChart2 = _interopRequireDefault(_lineChart);\n\nfunction _interopRequireDefault(obj) { return obj && obj.__esModule ? obj : { default: obj }; }","map":{"mappings":[{"generated":{"line":3,"column":0},"source":"getMood.js","original":{"line":1,"column":0}}],"sources":{"getMood.js":"import myChart from './lineChart';"},"lineCount":null}},"hash":"adcd9831e9100a18152aaa05543afce8","cacheData":{"env":{}}}